{
  "timestamp": 1770168650000,
  "state": "active",
  "task": "Expanding CJ Status to show thinking & planning",
  "plan": {
    "current": "Dashboard UI Refinement",
    "goal": "Create clean, informative command center",
    "progress": "Phase 3 of 4",
    "phase": "Balancing detail vs clarity",
    "next": "Add thinking/planning visibility",
    "why": "Jason wants to see my decision-making process, not just actions"
  },
  "thinking": "Just realized Jason wants MORE detail, not less. Need to show what plan I'm following, where I am in it, and why I'm making each decision.",
  "stats": {
    "🤖 Bots": "5 active",
    "💬 Tokens": "118k",
    "⏱️ Uptime": "4h 30m",
    "✅ Health": "All systems operational"
  }
}
